jewei_mssql_mcp_server-0.1.6.dist-info/licenses/LICENSE
mcp_server_jewei/__init__.py
mcp_server_jewei/app_config.py
mcp_server_jewei/core.py
mcp_server_jewei/server.py
jewei_mssql_mcp_server-0.1.6.dist-info/METADATA
jewei_mssql_mcp_server-0.1.6.dist-info/WHEEL
jewei_mssql_mcp_server-0.1.6.dist-info/entry_points.txt
jewei_mssql_mcp_server-0.1.6.dist-info/top_level.txt
jewei_mssql_mcp_server-0.1.6.dist-info/RECORD
