Metadata-Version: 2.4
Name: jewei-mssql-mcp-server
Version: 0.1.6
Summary: MSSQL MCP服务器，用于执行Microsoft SQL Server的数据查询和表结构查询操作
Author-email: Jewei <jewei@jeweis.com>
License: MIT License
Project-URL: Homepage, https://github.com/jeweis/jewei-mssql-mcp-server
Project-URL: Repository, https://github.com/jeweis/jewei-mssql-mcp-server
Project-URL: Issues, https://github.com/jeweis/jewei-mssql-mcp-server/issues
Keywords: mcp,sql-server,mssql,database,query
Classifier: Programming Language :: Python :: 3
Classifier: Operating System :: OS Independent
Classifier: Topic :: Database :: Database Engines/Servers
Requires-Python: >=3.8
License-File: LICENSE
Requires-Dist: fastmcp>=0.1.0
Requires-Dist: sqlalchemy>=1.4.0
Requires-Dist: pyodbc>=4.0.30
Requires-Dist: python-dotenv>=0.19.0
Requires-Dist: mcp[cli]>=1.0.0
Provides-Extra: dev
Requires-Dist: pytest>=7.0; extra == "dev"
Requires-Dist: ruff>=0.5.4; extra == "dev"
Dynamic: license-file
